fpga/rgb_mixer.v
`default_nettype none
`timescale 1ns/1ns

module rgb_mixer (
    input clk,
    input reset,
    input enc0_a,
    input enc0_b,
    input enc1_a,
    input enc1_b,
    input enc2_a,
    input enc2_b,
    output pwm0_out,
    output pwm1_out,
    output pwm2_out
);
    wire enc0_a_db, enc0_b_db;
    wire enc1_a_db, enc1_b_db;
    wire enc2_a_db, enc2_b_db;
    wire [7:0] enc0, enc1, enc2;
    wire new_clk;

    clock_divider clock_slow(.clk(clk), .clk_slow(new_clk));

    // debouncers, 2 for each encoder
    debounce #(.HIST_LEN(8)) debounce0_a(.clk(new_clk), .reset(reset), .button(enc0_a), .debounced(enc0_a_db));
    debounce #(.HIST_LEN(8)) debounce0_b(.clk(new_clk), .reset(reset), .button(enc0_b), .debounced(enc0_b_db));

    debounce #(.HIST_LEN(8)) debounce1_a(.clk(new_clk), .reset(reset), .button(enc1_a), .debounced(enc1_a_db));
    debounce #(.HIST_LEN(8)) debounce1_b(.clk(new_clk), .reset(reset), .button(enc1_b), .debounced(enc1_b_db));

    debounce #(.HIST_LEN(8)) debounce2_a(.clk(new_clk), .reset(reset), .button(enc2_a), .debounced(enc2_a_db));
    debounce #(.HIST_LEN(8)) debounce2_b(.clk(new_clk), .reset(reset), .button(enc2_b), .debounced(enc2_b_db));

    // encoders
    encoder #(.WIDTH(8)) encoder0(.clk(new_clk), .reset(reset), .a(enc0_a_db), .b(enc0_b_db), .value(enc0));
    encoder #(.WIDTH(8)) encoder1(.clk(new_clk), .reset(reset), .a(enc1_a_db), .b(enc1_b_db), .value(enc1));
    encoder #(.WIDTH(8)) encoder2(.clk(new_clk), .reset(reset), .a(enc2_a_db), .b(enc2_b_db), .value(enc2));

    // pwm modules
    pwm #(.WIDTH(8)) pwm0(.clk(new_clk), .reset(reset), .out(pwm0_out), .level(enc0));
    pwm #(.WIDTH(8)) pwm1(.clk(new_clk), .reset(reset), .out(pwm1_out), .level(enc1));
    pwm #(.WIDTH(8)) pwm2(.clk(new_clk), .reset(reset), .out(pwm2_out), .level(enc2));

endmodule

module clock_divider(
    input clk,
    output reg clk_slow
);
    reg [7:0] counter;
    reg top_bit;

    always @(posedge clk) begin
        counter <= counter + 1'b1;
        top_bit <= counter[7];
        clk_slow <= top_bit;
    end
endmodule

module debounce #(
    parameter HIST_LEN = 8
)( 
    input wire reset,
    input wire clk,
    input wire button,
    output reg debounced
);
    localparam on_value = 2 ** HIST_LEN - 1;
    reg [HIST_LEN-1:0] button_hist;

    always @(posedge clk) begin
        if (reset) begin
            button_hist <= 0;
            debounced <= 1'b0;
        end else begin
            button_hist <= {button_hist[HIST_LEN-2:0], button};
            if (button_hist == on_value)
                debounced <= 1'b1;
            else if (button_hist == {HIST_LEN{1'b0}})
                debounced <= 1'b0;
        end
    end 
endmodule 

module encoder #(
    parameter WIDTH = 8,
    parameter INCREMENT = 1'b1
)(
    input wire clk,
    input wire reset,
    input wire a,
    input wire b,
    output reg [WIDTH-1:0] value
);
    reg old_a, old_b;

    always @(posedge clk) begin
        if (reset) begin
            value <= 0;
            old_a <= 0;
            old_b <= 0;
        end else begin
            old_a <= a;
            old_b <= b;
            case ({a, old_a, b, old_b})
                4'b1000, 4'b0111: value <= value + INCREMENT;
                4'b0010, 4'b1101: value <= value - INCREMENT;
                default: value <= value;
            endcase
        end
    end
endmodule

module pwm #(
    parameter WIDTH = 8,
    parameter INVERT = 0
)(
    input wire clk,
    input wire reset,
    output wire out,
    input wire [WIDTH-1:0] level
);
    reg [WIDTH-1:0] counter;
    wire pwm_on = counter < level;

    always @(posedge clk) begin
        if (reset) begin
            counter <= 1'b0;
        end else begin
            counter <= counter + 1'b1;
        end
    end

    assign out = reset ? 1'b0 :
                 (INVERT == 1'b0 ? pwm_on : !pwm_on);
endmodule

pwm.vcd
$date
	Wed May 15 13:14:39 2024
$end
$version
	Icarus Verilog
$end
$timescale
	1ns
$end
$scope module pwm $end
$var wire 1 ! clk $end
$var wire 8 " level [7:0] $end
$var wire 1 # reset $end
$var wire 1 $ pwm_on $end
$var wire 1 % out $end
$var parameter 32 & INVERT $end
$var parameter 32 ' WIDTH $end
$var reg 8 ( counter [7:0] $end
$upscope $end
$enddefinitions $end
$comment Show the parameter values. $end
$dumpall
b1000 '
b0 &
$end
#0
$dumpvars
b0 (
0%
1$
1#
b1 "
1!
$end
#5000
0!
#10000
1!
#15000
0!
#20000
1!
#25000
0!
#30000
1!
#35000
0!
#40000
1%
0#
1!
#45000
0!
#50000
0%
0$
b1 (
1!
#55000
0!
#60000
1#
b10 (
1!
#65000
0!
#70000
1$
b0 (
1!
#75000
0!
#80000
1!
#85000
0!
#90000
1!
#95000
0!
#100000
1!
#105000
0!
#110000
1%
0#
1!
#115000
0!
#120000
0%
0$
b1 (
1!
#125000
0!
#130000
1#
b10 (
1!
#135000
0!
#140000
1$
b0 (
1!
#145000
0!
#150000
1!
#155000
0!
#160000
1!
#165000
0!
#170000
1!
#175000
0!
#180000
1%
0#
1!
#185000
0!
#190000
0%
0$
b1 (
1!
#195000
0!
#200000
1#
b10 (
1!
#205000
0!
#210000
1$
b0 (
1!
#215000
0!
#220000
1!
#225000
0!
#230000
1!
#235000
0!
#240000
1!
#245000
0!
#250000
1%
0#
1!
#255000
0!
#260000
0%
0$
b1 (
1!
#265000
0!
#270000
1#
b10 (
1!
#275000
0!
#280000
1$
b0 (
1!
#285000
0!
#290000
1!
#295000
0!
#300000
1!
#305000
0!
#310000
1!
#315000
0!
#320000
1%
0#
1!
#325000
0!
#330000
0%
0$
b1 (
1!
#335000
0!
#340000
1#
b10 (
1!
#345000
0!
#350000
1$
b0 (
1!
#355000
0!
#360000
1!
#365000
0!
#370000
1!
#375000
0!
#380000
1!
#385000
0!
#390000
1%
0#
1!
#395000
0!
#400000
0%
0$
b1 (
1!
#405000
0!
#410000
1#
b10 (
1!
#415000
0!
#420000
1$
b0 (
1!
#425000
0!
#430000
1!
#435000
0!
#440000
1!
#445000
0!
#450000
1!
#455000
0!
#460000
1%
0#
1!
#465000
0!
#470000
0%
0$
b1 (
1!
#475000
0!
#480000
1#
b10 (
1!
#485000
0!
#490000
1$
b0 (
1!
#495000
0!
#500000
1!
#505000
0!
#510000
1!
#515000
0!
#520000
1!
#525000
0!
#530000
1%
0#
1!
#535000
0!
#540000
0%
0$
b1 (
1!
#545000
0!
#550000
1#
b10 (
1!
#555000
0!
#560000
1$
b0 (
1!
#565000
0!
#570000
1!
#575000
0!
#580000
1!
#585000
0!
#590000
1!
#595000
0!
#600000
1%
0#
1!
#605000
0!
#610000
0%
0$
b1 (
1!
#615000
0!
#620000
1#
b10 (
1!
#625000
0!
#630000
1$
b0 (
1!
#635000
0!
#640000
1!
#645000
0!
#650000
1!
#655000
0!
#660000
1!
#665000
0!
#670000
1%
0#
1!
#675000
0!
#680000
0%
0$
b1 (
1!
#685000
0!
#690000
1#
b10 (
1!
#695000
0!
#700000
1$
b0 (
1!
#705000
0!
#710000
1!
#715000
0!
#720000
1!
#725000
0!
#730000
1!
#735000
0!
#740000
1%
0#
1!
#745000
0!
#750000
0%
0$
b1 (
1!
#755000
0!
#760000
1#
b10 (
1!
#765000
0!
#770000
1$
b0 (
1!
#775000
0!
#780000
1!
#785000
0!
#790000
1!
#795000
0!
#800000
1!
#805000
0!
#810000
1%
0#
1!
#815000
0!
#820000
0%
0$
b1 (
1!
#825000
0!
#830000
1#
b10 (
1!
#835000
0!
#840000
1$
b0 (
1!
#845000
0!
#850000
1!
#855000
0!
#860000
1!
#865000
0!
#870000
1!
#875000
0!
#880000
1%
0#
1!
#885000
0!
#890000
0%
0$
b1 (
1!
#895000
0!
#900000
b10 (
1!
